n3pm_progress/__init__.py
n3pm_progress/apps.py
n3pm_progress-0.0.2.dist-info/METADATA
n3pm_progress-0.0.2.dist-info/WHEEL
n3pm_progress-0.0.2.dist-info/top_level.txt
n3pm_progress-0.0.2.dist-info/RECORD
